auto_code/__init__.py
auto_code/auto_code.py
auto_code/back_end_bot.py
auto_code/front_end_bot.py
auto_code/html_css_bot.py
auto_code/java_script_bot.py
auto_code/md_bot.py
auto_code/network_bot.py
auto_code/qa_bot.py
auto_code/scripting_bot.py
auto_code/sql_dbt_yml_bot.py
cli/__init__.py
cli/auto_code.py
cli/back_end.py
cli/front_end.py
cli/html_css.py
cli/java_script.py
cli/md_bot.py
cli/network.py
cli/qa.py
cli/scripting_bot.py
cli/sql_dbt_yml.py
cowgirl_ai_auto_code-1.5.2.dist-info/LICENSE
cowgirl_ai_auto_code-1.5.2.dist-info/METADATA
cowgirl_ai_auto_code-1.5.2.dist-info/WHEEL
cowgirl_ai_auto_code-1.5.2.dist-info/entry_points.txt
cowgirl_ai_auto_code-1.5.2.dist-info/top_level.txt
cowgirl_ai_auto_code-1.5.2.dist-info/RECORD
