Metadata-Version: 2.1
Name: cowgirl-ai-auto-code
Version: 1.5.2
Summary: Cowgirl AI - Auto Code
Home-page: https://github.com/Cowgirl-AI/auto-code
Author: Tera Earlywine
Author-email: dev@teraearlywine.com
Requires-Python: >=3.10
License-File: LICENSE
